{
	"name": "scheduled_trigger",
	"properties": {
		"annotations": [],
		"runtimeState": "Stopped",
		"pipelines": [
			{
				"pipelineReference": {
					"referenceName": "copy-all-tables",
					"type": "PipelineReference"
				}
			}
		],
		"type": "ScheduleTrigger",
		"typeProperties": {
			"recurrence": {
				"frequency": "Day",
				"interval": 1,
				"startTime": "2025-08-01T10:48:00",
				"timeZone": "SE Asia Standard Time",
				"schedule": {
					"minutes": [
						0
					],
					"hours": [
						10
					]
				}
			}
		}
	}
}